robot_test_creator/__init__.py
robot_test_creator/excel2suites.py
robot_test_creator-1.2.0.dist-info/entry_points.txt
robot_test_creator-1.2.0.dist-info/METADATA
robot_test_creator-1.2.0.dist-info/WHEEL
robot_test_creator-1.2.0.dist-info/RECORD
